{
    "tutorialSidebar": [
      "intro",
      {
        "type": "category",
        "label": "入门",
        "link": {
          "type": "generated-index"
        },
        "collapsed": false,
        "items": [
          "getting-started/prepare",
          {
            "type": "category",
            "label": "安装指南",
            "link": {
              "type": "generated-index"
            },
            "items": [
              "getting-started/install/docker-compose",
              "getting-started/install/docker"
            ]
          }
        ]
      },
      "about"
    ]
  }
  